s3_storage_provider.py
enhanced_s3_storage_provider-1.7.0.data/scripts/s3_media_upload
enhanced_s3_storage_provider-1.7.0.dist-info/licenses/LICENSE
enhanced_s3_storage_provider-1.7.0.dist-info/METADATA
enhanced_s3_storage_provider-1.7.0.dist-info/WHEEL
enhanced_s3_storage_provider-1.7.0.dist-info/top_level.txt
enhanced_s3_storage_provider-1.7.0.dist-info/RECORD
