Metadata-Version: 2.4
Name: enhanced-s3-storage-provider
Version: 1.7.0
Summary: A storage provider which can fetch and store media in Amazon S3.
Home-page: https://github.com/elyesbenamor/synapse-s3-storage-provider.git
Author: matrix.org team and contributors
License: Apache-2.0
Classifier: Programming Language :: Python :: 3
License-File: LICENSE
Requires-Dist: boto3<2.0,>=1.20.0
Requires-Dist: botocore<2.0,>=1.23.0
Requires-Dist: humanize<5.0,>=4.0
Requires-Dist: psycopg2-binary<3.0,>=2.7.5
Requires-Dist: PyYAML<7.0,>=5.4
Requires-Dist: tqdm<5.0,>=4.26.0
Requires-Dist: Twisted
Requires-Dist: minio
Dynamic: author
Dynamic: classifier
Dynamic: description
Dynamic: description-content-type
Dynamic: home-page
Dynamic: license
Dynamic: license-file
Dynamic: requires-dist
Dynamic: summary
